apipod/CONSTS.py
apipod/__init__.py
apipod/apipod.py
apipod/cli.py
apipod/settings.py
apipod/compatibility/HealthCheck.py
apipod/compatibility/LimitedUploadFile.py
apipod/compatibility/__init__.py
apipod/compatibility/upload.py
apipod/core/__init__.py
apipod/core/utils.py
apipod/core/job/__init__.py
apipod/core/job/base_job.py
apipod/core/job/job_progress.py
apipod/core/job/job_result.py
apipod/core/job_queues/job_queue.py
apipod/core/job_queues/job_queue_interface.py
apipod/core/job_queues/job_store.py
apipod/core/job_queues/redis_job_queue.py
apipod/core/routers/__init__.py
apipod/core/routers/_exceptions.py
apipod/core/routers/_fastapi_router.py
apipod/core/routers/_runpod_router.py
apipod/core/routers/_socaity_router.py
apipod/core/routers/router_mixins/__init__.py
apipod/core/routers/router_mixins/_base_file_handling_mixin.py
apipod/core/routers/router_mixins/_fast_api_exception_handling.py
apipod/core/routers/router_mixins/_fast_api_file_handling_mixin.py
apipod/core/routers/router_mixins/_queue_mixin.py
apipod/deploy/deployment_manager.py
apipod/deploy/docker_factory.py
apipod/deploy/scanner.py
apipod/deploy/detectors/IDetector.py
apipod/deploy/detectors/__init__.py
apipod/deploy/detectors/dependencies.py
apipod/deploy/detectors/entrypoint.py
apipod/deploy/detectors/env.py
apipod/deploy/detectors/framework.py
apipod/deploy/detectors/project_root.py
apipod-1.0.1.dist-info/licenses/LICENSE
apipod-1.0.1.dist-info/METADATA
apipod-1.0.1.dist-info/WHEEL
apipod-1.0.1.dist-info/entry_points.txt
apipod-1.0.1.dist-info/top_level.txt
apipod-1.0.1.dist-info/RECORD
